{
  "id": "3456f5ad-ea22-42e2-8a5d-1cbc356ed8d0",
  "prevId": "225d2bc4-9bb8-42c3-aaab-c3d5a76bd6e5",
  "version": "7",
  "dialect": "postgresql",
  "tables": {
    "public.player_achievement_diaries": {
      "name": "player_achievement_diaries",
      "schema": "",
      "columns": {
        "id": {
          "name": "id",
          "type": "uuid",
          "primaryKey": true,
          "notNull": true,
          "default": "gen_random_uuid()"
        },
        "player_name": {
          "name": "player_name",
          "type": "varchar(12)",
          "primaryKey": false,
          "notNull": true
        },
        "location": {
          "name": "location",
          "type": "varchar(50)",
          "primaryKey": false,
          "notNull": true
        },
        "tier": {
          "name": "tier",
          "type": "varchar(20)",
          "primaryKey": false,
          "notNull": true
        },
        "completed": {
          "name": "completed",
          "type": "boolean",
          "primaryKey": false,
          "notNull": true,
          "default": false
        },
        "created_at": {
          "name": "created_at",
          "type": "timestamp",
          "primaryKey": false,
          "notNull": true,
          "default": "now()"
        },
        "updated_at": {
          "name": "updated_at",
          "type": "timestamp",
          "primaryKey": false,
          "notNull": true,
          "default": "now()"
        }
      },
      "indexes": {},
      "foreignKeys": {},
      "compositePrimaryKeys": {},
      "uniqueConstraints": {},
      "policies": {},
      "checkConstraints": {},
      "isRLSEnabled": false
    },
    "public.player_acquired_items": {
      "name": "player_acquired_items",
      "schema": "",
      "columns": {
        "id": {
          "name": "id",
          "type": "uuid",
          "primaryKey": true,
          "notNull": true,
          "default": "gen_random_uuid()"
        },
        "player_name": {
          "name": "player_name",
          "type": "varchar(12)",
          "primaryKey": false,
          "notNull": true
        },
        "item_name": {
          "name": "item_name",
          "type": "text",
          "primaryKey": false,
          "notNull": true
        },
        "item_id": {
          "name": "item_id",
          "type": "integer",
          "primaryKey": false,
          "notNull": true
        },
        "count": {
          "name": "count",
          "type": "integer",
          "primaryKey": false,
          "notNull": true,
          "default": 1
        },
        "item_category": {
          "name": "item_category",
          "type": "varchar(100)",
          "primaryKey": false,
          "notNull": true
        },
        "date_first_logged": {
          "name": "date_first_logged",
          "type": "timestamp",
          "primaryKey": false,
          "notNull": true
        },
        "created_at": {
          "name": "created_at",
          "type": "timestamp",
          "primaryKey": false,
          "notNull": true,
          "default": "now()"
        }
      },
      "indexes": {},
      "foreignKeys": {},
      "compositePrimaryKeys": {},
      "uniqueConstraints": {
        "player_acquired_items_player_name_item_name_unique": {
          "name": "player_acquired_items_player_name_item_name_unique",
          "nullsNotDistinct": false,
          "columns": ["player_name", "item_name"]
        }
      },
      "policies": {},
      "checkConstraints": {},
      "isRLSEnabled": false
    },
    "public.players": {
      "name": "players",
      "schema": "",
      "columns": {
        "player_name": {
          "name": "player_name",
          "type": "varchar(12)",
          "primaryKey": true,
          "notNull": true
        },
        "join_date": {
          "name": "join_date",
          "type": "date",
          "primaryKey": false,
          "notNull": true
        },
        "ehb": {
          "name": "ehb",
          "type": "real",
          "primaryKey": false,
          "notNull": true,
          "default": 0
        },
        "ehp": {
          "name": "ehp",
          "type": "real",
          "primaryKey": false,
          "notNull": true,
          "default": 0
        },
        "combat_achievement_tier": {
          "name": "combat_achievement_tier",
          "type": "varchar(50)",
          "primaryKey": false,
          "notNull": true,
          "default": "'None'"
        },
        "rank": {
          "name": "rank",
          "type": "varchar(50)",
          "primaryKey": false,
          "notNull": true
        },
        "proof_link": {
          "name": "proof_link",
          "type": "text",
          "primaryKey": false,
          "notNull": false
        },
        "collection_log_count": {
          "name": "collection_log_count",
          "type": "integer",
          "primaryKey": false,
          "notNull": true,
          "default": 0
        },
        "collection_log_total": {
          "name": "collection_log_total",
          "type": "integer",
          "primaryKey": false,
          "notNull": true,
          "default": 0
        },
        "total_level": {
          "name": "total_level",
          "type": "integer",
          "primaryKey": false,
          "notNull": true,
          "default": 32
        },
        "clue_count_beginner": {
          "name": "clue_count_beginner",
          "type": "integer",
          "primaryKey": false,
          "notNull": true,
          "default": 0
        },
        "clue_count_easy": {
          "name": "clue_count_easy",
          "type": "integer",
          "primaryKey": false,
          "notNull": true,
          "default": 0
        },
        "clue_count_medium": {
          "name": "clue_count_medium",
          "type": "integer",
          "primaryKey": false,
          "notNull": true,
          "default": 0
        },
        "clue_count_hard": {
          "name": "clue_count_hard",
          "type": "integer",
          "primaryKey": false,
          "notNull": true,
          "default": 0
        },
        "clue_count_elite": {
          "name": "clue_count_elite",
          "type": "integer",
          "primaryKey": false,
          "notNull": true,
          "default": 0
        },
        "clue_count_master": {
          "name": "clue_count_master",
          "type": "integer",
          "primaryKey": false,
          "notNull": true,
          "default": 0
        },
        "tzhaar_cape": {
          "name": "tzhaar_cape",
          "type": "varchar(50)",
          "primaryKey": false,
          "notNull": true,
          "default": "'None'"
        },
        "has_blood_torva": {
          "name": "has_blood_torva",
          "type": "boolean",
          "primaryKey": false,
          "notNull": true,
          "default": false
        },
        "has_radiant_oathplate": {
          "name": "has_radiant_oathplate",
          "type": "boolean",
          "primaryKey": false,
          "notNull": true,
          "default": false
        },
        "has_dizanas_quiver": {
          "name": "has_dizanas_quiver",
          "type": "boolean",
          "primaryKey": false,
          "notNull": true,
          "default": false
        },
        "has_achievement_diary_cape": {
          "name": "has_achievement_diary_cape",
          "type": "boolean",
          "primaryKey": false,
          "notNull": true,
          "default": false
        },
        "combat_bonus_points": {
          "name": "combat_bonus_points",
          "type": "real",
          "primaryKey": false,
          "notNull": true,
          "default": 0
        },
        "skilling_bonus_points": {
          "name": "skilling_bonus_points",
          "type": "real",
          "primaryKey": false,
          "notNull": true,
          "default": 0
        },
        "collection_log_bonus_points": {
          "name": "collection_log_bonus_points",
          "type": "real",
          "primaryKey": false,
          "notNull": true,
          "default": 0
        },
        "notable_items_bonus_points": {
          "name": "notable_items_bonus_points",
          "type": "real",
          "primaryKey": false,
          "notNull": true,
          "default": 0
        },
        "created_at": {
          "name": "created_at",
          "type": "timestamp",
          "primaryKey": false,
          "notNull": true,
          "default": "now()"
        },
        "updated_at": {
          "name": "updated_at",
          "type": "timestamp",
          "primaryKey": false,
          "notNull": true,
          "default": "now()"
        }
      },
      "indexes": {},
      "foreignKeys": {},
      "compositePrimaryKeys": {},
      "uniqueConstraints": {},
      "policies": {},
      "checkConstraints": {},
      "isRLSEnabled": false
    }
  },
  "enums": {},
  "schemas": {},
  "sequences": {},
  "roles": {},
  "policies": {},
  "views": {},
  "_meta": {
    "columns": {},
    "schemas": {},
    "tables": {}
  }
}
